robotpy_installer/__init__.py
robotpy_installer/__main__.py
robotpy_installer/_pipstub.py
robotpy_installer/cacheserver.py
robotpy_installer/cli_deploy.py
robotpy_installer/cli_deploy_info.py
robotpy_installer/cli_init.py
robotpy_installer/cli_installer.py
robotpy_installer/cli_project.py
robotpy_installer/cli_sync.py
robotpy_installer/cli_undeploy.py
robotpy_installer/errors.py
robotpy_installer/frcKillRobot.sh
robotpy_installer/installer.py
robotpy_installer/pypackages.py
robotpy_installer/pyproject.py
robotpy_installer/roborio_utils.py
robotpy_installer/robotfinder.py
robotpy_installer/sshcontroller.py
robotpy_installer/utils.py
robotpy_installer/version.py
robotpy_installer/wpilib_preferences.py
robotpy_installer-2025.1.1.dist-info/METADATA
robotpy_installer-2025.1.1.dist-info/WHEEL
robotpy_installer-2025.1.1.dist-info/entry_points.txt
robotpy_installer-2025.1.1.dist-info/licenses/LICENSE
robotpy_installer-2025.1.1.dist-info/RECORD
