Metadata-Version: 2.4
Name: robotpy-installer
Version: 2025.1.1
Summary: Installation utility program for RobotPy
Project-URL: Source code, https://github.com/robotpy/robotpy-installer
Author-email: RobotPy Development Team <robotpy@googlegroups.com>
License: Copyright © 2011-2020 Dustin Spicuzza and contributors
License-File: LICENSE
Classifier: Development Status :: 5 - Production/Stable
Classifier: Intended Audience :: Developers
Classifier: License :: OSI Approved :: BSD License
Classifier: Operating System :: OS Independent
Classifier: Programming Language :: Python :: 3 :: Only
Classifier: Topic :: Scientific/Engineering
Classifier: Topic :: Software Development
Requires-Python: >=3.9
Requires-Dist: packaging>=23.2
Requires-Dist: paramiko
Requires-Dist: pip
Requires-Dist: pynetconsole~=2.0.2
Requires-Dist: robotpy-cli~=2024.0
Requires-Dist: tomli
Requires-Dist: tomlkit
